{
  "data": {
    "tokenDayDatas": [
      {
        "token": {
          "symbol": "USDT"
        },
        "date": 1653350400,
        "dailyVolumeUSD": "1862586.651753966235216055429509277",
        "dailyTxns": "728",
        "priceUSD": "1.000197904832876738129728857875025"
      },
      {
        "token": {
          "symbol": "USDT"
        },
        "date": 1653264000,
        "dailyVolumeUSD": "10389273.66953105305443994270502076",
        "dailyTxns": "2693",
        "priceUSD": "0.9988715885924540431569979772454708"
      },
      {
        "token": {
          "symbol": "USDT"
        },
        "date": 1653177600,
        "dailyVolumeUSD": "5962638.856363624666612482298906776",
        "dailyTxns": "2173",
        "priceUSD": "0.999844298826164129507570135998234"
      },
      {
        "token": {
          "symbol": "USDT"
        },
        "date": 1653091200,
        "dailyVolumeUSD": "6339033.337521993475736980002837486",
        "dailyTxns": "2428",
        "priceUSD": "1.000071881731992315249170686502449"
      },
      {
        "token": {
          "symbol": "USDT"
        },
        "date": 1653004800,
        "dailyVolumeUSD": "10297186.95489166641972147871451365",
        "dailyTxns": "2661",
        "priceUSD": "0.9985998972366647628558899888175015"
      },
      {
        "token": {
          "symbol": "USDT"
        },
        "date": 1652918400,
        "dailyVolumeUSD": "11555212.03772264550265425579730946",
        "dailyTxns": "3006",
        "priceUSD": "0.9996257122954831467516459520614023"
      },
      {
        "token": {
          "symbol": "USDT"
        },
        "date": 1652832000,
        "dailyVolumeUSD": "17019945.63061299602899225807835447",
        "dailyTxns": "3473",
        "priceUSD": "0.9991971721999385869481863222384029"
      },
      {
        "token": {
          "symbol": "USDT"
        },
        "date": 1652745600,
        "dailyVolumeUSD": "11736910.1627872177625122110786343",
        "dailyTxns": "2763",
        "priceUSD": "0.9990737168898192223507986498326046"
      },
      {
        "token": {
          "symbol": "USDT"
        },
        "date": 1652659200,
        "dailyVolumeUSD": "14454385.43959191128175782834976475",
        "dailyTxns": "3130",
        "priceUSD": "0.9984975502390006838708029536329752"
      },
      {
        "token": {
          "symbol": "USDT"
        },
        "date": 1652572800,
        "dailyVolumeUSD": "10892770.77781904075129268245909065",
        "dailyTxns": "3097",
        "priceUSD": "0.9995643822382413508111233541056855"
      },
      {
        "token": {
          "symbol": "USDT"
        },
        "date": 1652486400,
        "dailyVolumeUSD": "13890363.8848659491397020703111908",
        "dailyTxns": "3338",
        "priceUSD": "0.9987418842550497661631567346190828"
      },
      {
        "token": {
          "symbol": "USDT"
        },
        "date": 1652400000,
        "dailyVolumeUSD": "26735220.1521361648656524941437611",
        "dailyTxns": "3819",
        "priceUSD": "0.9982818871702176282102790724924316"
      },
      {
        "token": {
          "symbol": "USDT"
        },
        "date": 1652313600,
        "dailyVolumeUSD": "177530988.4524393226012126696470598",
        "dailyTxns": "5513",
        "priceUSD": "0.9984919762924442806843187027404874"
      },
      {
        "token": {
          "symbol": "USDT"
        },
        "date": 1652227200,
        "dailyVolumeUSD": "87777802.47614971903663737388836813",
        "dailyTxns": "5002",
        "priceUSD": "0.9970111499203769971284718393830037"
      },
      {
        "token": {
          "symbol": "USDT"
        },
        "date": 1652140800,
        "dailyVolumeUSD": "34597693.84144554331486849146819804",
        "dailyTxns": "3962",
        "priceUSD": "0.9988391778920568707453013012403763"
      },
      {
        "token": {
          "symbol": "USDT"
        },
        "date": 1652054400,
        "dailyVolumeUSD": "40300804.97390320230258779921336884",
        "dailyTxns": "4130",
        "priceUSD": "0.9991092048878186783295317542343558"
      },
      {
        "token": {
          "symbol": "USDT"
        },
        "date": 1651968000,
        "dailyVolumeUSD": "23383114.53993823843953340038792484",
        "dailyTxns": "3132",
        "priceUSD": "0.9993406652230243433481738245937357"
      },
      {
        "token": {
          "symbol": "USDT"
        },
        "date": 1651881600,
        "dailyVolumeUSD": "9023959.42660145231675903941745154",
        "dailyTxns": "2448",
        "priceUSD": "0.9986889975370764397823051694565941"
      },
      {
        "token": {
          "symbol": "USDT"
        },
        "date": 1651795200,
        "dailyVolumeUSD": "21254210.19857212313534985459654378",
        "dailyTxns": "3016",
        "priceUSD": "0.9994076881120340890008941543706428"
      },
      {
        "token": {
          "symbol": "USDT"
        },
        "date": 1651708800,
        "dailyVolumeUSD": "20068499.50409188180784140397500303",
        "dailyTxns": "3015",
        "priceUSD": "0.9998631908761288841881002257131419"
      },
      {
        "token": {
          "symbol": "USDT"
        },
        "date": 1651622400,
        "dailyVolumeUSD": "25282080.64521353094397347721596272",
        "dailyTxns": "4865",
        "priceUSD": "1.000137337134392087167586081271359"
      },
      {
        "token": {
          "symbol": "USDT"
        },
        "date": 1651536000,
        "dailyVolumeUSD": "11165757.28876223682201589111393302",
        "dailyTxns": "2437",
        "priceUSD": "0.9988986855487430348469956387153259"
      },
      {
        "token": {
          "symbol": "USDT"
        },
        "date": 1651449600,
        "dailyVolumeUSD": "11523335.03130931439781436580104182",
        "dailyTxns": "1973",
        "priceUSD": "1.000500716712301528997744632737613"
      },
      {
        "token": {
          "symbol": "USDT"
        },
        "date": 1651363200,
        "dailyVolumeUSD": "16255463.22928720622150011207490238",
        "dailyTxns": "1949",
        "priceUSD": "0.9984810013630148123321544029233541"
      },
      {
        "token": {
          "symbol": "USDT"
        },
        "date": 1651276800,
        "dailyVolumeUSD": "14511652.2573377294669007600762456",
        "dailyTxns": "2726",
        "priceUSD": "0.9999480564288368655251604130567474"
      },
      {
        "token": {
          "symbol": "USDT"
        },
        "date": 1651190400,
        "dailyVolumeUSD": "14035623.429333301927348059120259",
        "dailyTxns": "2938",
        "priceUSD": "0.9994539267773656686627446220625481"
      },
      {
        "token": {
          "symbol": "USDT"
        },
        "date": 1651104000,
        "dailyVolumeUSD": "15027178.65482154631455653727729645",
        "dailyTxns": "2783",
        "priceUSD": "0.9998296260097209656330809983384025"
      },
      {
        "token": {
          "symbol": "USDT"
        },
        "date": 1651017600,
        "dailyVolumeUSD": "15489327.12724771705713353757339657",
        "dailyTxns": "2629",
        "priceUSD": "1.000407129478020315431005840280862"
      },
      {
        "token": {
          "symbol": "USDT"
        },
        "date": 1650931200,
        "dailyVolumeUSD": "26515476.91226018694583629723650292",
        "dailyTxns": "3073",
        "priceUSD": "1.000591757711501232891731659668193"
      },
      {
        "token": {
          "symbol": "USDT"
        },
        "date": 1650844800,
        "dailyVolumeUSD": "23426444.51659631800207693152169079",
        "dailyTxns": "3251",
        "priceUSD": "0.9991690823404692902904293587800324"
      },
      {
        "token": {
          "symbol": "USDT"
        },
        "date": 1650758400,
        "dailyVolumeUSD": "10406205.73217165714986499884868455",
        "dailyTxns": "2891",
        "priceUSD": "1.002957883549786736696555548228764"
      },
      {
        "token": {
          "symbol": "USDT"
        },
        "date": 1650672000,
        "dailyVolumeUSD": "16530256.85559606749258907596757013",
        "dailyTxns": "4232",
        "priceUSD": "0.9990960004484952510461240905489543"
      },
      {
        "token": {
          "symbol": "USDT"
        },
        "date": 1650585600,
        "dailyVolumeUSD": "14448372.18134871040653709389939569",
        "dailyTxns": "2865",
        "priceUSD": "1.000015742156375466231385939338521"
      },
      {
        "token": {
          "symbol": "USDT"
        },
        "date": 1650499200,
        "dailyVolumeUSD": "24292914.09602992596381327005325981",
        "dailyTxns": "3691",
        "priceUSD": "0.9994535127287590519993522342233523"
      },
      {
        "token": {
          "symbol": "USDT"
        },
        "date": 1650412800,
        "dailyVolumeUSD": "15976545.18806764288143060643345572",
        "dailyTxns": "3095",
        "priceUSD": "1.000685417252824408285760504410229"
      },
      {
        "token": {
          "symbol": "USDT"
        },
        "date": 1650326400,
        "dailyVolumeUSD": "15441622.37172462028996922542250856",
        "dailyTxns": "3354",
        "priceUSD": "1.000770728939701798470997474032283"
      },
      {
        "token": {
          "symbol": "USDT"
        },
        "date": 1650240000,
        "dailyVolumeUSD": "17053348.58772094673099149698884533",
        "dailyTxns": "3777",
        "priceUSD": "0.9994475988336146521057822154197189"
      },
      {
        "token": {
          "symbol": "USDT"
        },
        "date": 1650153600,
        "dailyVolumeUSD": "14422445.76671873870219356643345856",
        "dailyTxns": "4428",
        "priceUSD": "0.999472832630088063189754252327197"
      },
      {
        "token": {
          "symbol": "USDT"
        },
        "date": 1650067200,
        "dailyVolumeUSD": "15533265.96433229420277814891244583",
        "dailyTxns": "4846",
        "priceUSD": "0.9997642387915939588092944308738986"
      },
      {
        "token": {
          "symbol": "USDT"
        },
        "date": 1649980800,
        "dailyVolumeUSD": "12626160.5686518263057098504406575",
        "dailyTxns": "3212",
        "priceUSD": "1.000103237039429167977696211696518"
      },
      {
        "token": {
          "symbol": "USDT"
        },
        "date": 1649894400,
        "dailyVolumeUSD": "13135352.7753892044929658536823066",
        "dailyTxns": "2941",
        "priceUSD": "1.000124722931888807724415745945771"
      },
      {
        "token": {
          "symbol": "USDT"
        },
        "date": 1649808000,
        "dailyVolumeUSD": "14903558.93120129051617763678437932",
        "dailyTxns": "2721",
        "priceUSD": "0.9999169323439092721492530303865484"
      },
      {
        "token": {
          "symbol": "USDT"
        },
        "date": 1649721600,
        "dailyVolumeUSD": "19212861.82803258478313381490734983",
        "dailyTxns": "3555",
        "priceUSD": "1.000615063019411798754712489172025"
      },
      {
        "token": {
          "symbol": "USDT"
        },
        "date": 1649635200,
        "dailyVolumeUSD": "25777656.67493463537217747222251278",
        "dailyTxns": "3845",
        "priceUSD": "1.000155508298060590503982943799936"
      },
      {
        "token": {
          "symbol": "USDT"
        },
        "date": 1649548800,
        "dailyVolumeUSD": "13482439.99653898348602802501060622",
        "dailyTxns": "2904",
        "priceUSD": "1.00017056037738383978254765844492"
      },
      {
        "token": {
          "symbol": "USDT"
        },
        "date": 1649462400,
        "dailyVolumeUSD": "23135161.54731858661169167084440934",
        "dailyTxns": "4258",
        "priceUSD": "1.000389839279565023238927489364352"
      },
      {
        "token": {
          "symbol": "USDT"
        },
        "date": 1649376000,
        "dailyVolumeUSD": "21115982.57337973574932661163776638",
        "dailyTxns": "3256",
        "priceUSD": "1.000171605895195600581854904486758"
      },
      {
        "token": {
          "symbol": "USDT"
        },
        "date": 1649289600,
        "dailyVolumeUSD": "19282079.862912799489792142113387",
        "dailyTxns": "2973",
        "priceUSD": "0.9992560329777366105177047171392886"
      },
      {
        "token": {
          "symbol": "USDT"
        },
        "date": 1649203200,
        "dailyVolumeUSD": "28046834.86547728390391313008739565",
        "dailyTxns": "3996",
        "priceUSD": "1.00034228649200420946892240664955"
      },
      {
        "token": {
          "symbol": "USDT"
        },
        "date": 1649116800,
        "dailyVolumeUSD": "23614532.9987480202128215466674459",
        "dailyTxns": "3488",
        "priceUSD": "1.00000033398606799388497624263712"
      },
      {
        "token": {
          "symbol": "USDT"
        },
        "date": 1649030400,
        "dailyVolumeUSD": "29188924.07189739978927810049893844",
        "dailyTxns": "3939",
        "priceUSD": "0.9996649426085643906316859946023313"
      },
      {
        "token": {
          "symbol": "USDT"
        },
        "date": 1648944000,
        "dailyVolumeUSD": "22318623.23138040851216373756736628",
        "dailyTxns": "3755",
        "priceUSD": "0.9992105428771015411716898126876074"
      },
      {
        "token": {
          "symbol": "USDT"
        },
        "date": 1648857600,
        "dailyVolumeUSD": "25557398.74814707342627239229130467",
        "dailyTxns": "4139",
        "priceUSD": "1.000285961075301653618742247755628"
      },
      {
        "token": {
          "symbol": "USDT"
        },
        "date": 1648771200,
        "dailyVolumeUSD": "24423365.12149152451273763087907944",
        "dailyTxns": "4176",
        "priceUSD": "1.001009750734729630982499863781671"
      },
      {
        "token": {
          "symbol": "USDT"
        },
        "date": 1648684800,
        "dailyVolumeUSD": "24496366.5820390758308433808481509",
        "dailyTxns": "4292",
        "priceUSD": "0.999770567547069529665617705341226"
      },
      {
        "token": {
          "symbol": "USDT"
        },
        "date": 1648598400,
        "dailyVolumeUSD": "20182871.63031061083241499356674447",
        "dailyTxns": "3777",
        "priceUSD": "1.00112088310234344022691961574874"
      },
      {
        "token": {
          "symbol": "USDT"
        },
        "date": 1648512000,
        "dailyVolumeUSD": "32245167.67555871048863536174614784",
        "dailyTxns": "4329",
        "priceUSD": "1.000428958474199341980372382452544"
      },
      {
        "token": {
          "symbol": "USDT"
        },
        "date": 1648425600,
        "dailyVolumeUSD": "25875430.28028539977062273388685707",
        "dailyTxns": "4267",
        "priceUSD": "1.002240265184853326511647417709791"
      },
      {
        "token": {
          "symbol": "USDT"
        },
        "date": 1648339200,
        "dailyVolumeUSD": "16954400.10647372108826584785713939",
        "dailyTxns": "3898",
        "priceUSD": "1.001851836491310175284998007574442"
      },
      {
        "token": {
          "symbol": "USDT"
        },
        "date": 1648252800,
        "dailyVolumeUSD": "14587986.04474954636447718043148328",
        "dailyTxns": "3244",
        "priceUSD": "1.001616469120625735239260555271313"
      },
      {
        "token": {
          "symbol": "USDT"
        },
        "date": 1648166400,
        "dailyVolumeUSD": "17423782.70492384351604004925246205",
        "dailyTxns": "3494",
        "priceUSD": "1.000301267171132697353342037447611"
      },
      {
        "token": {
          "symbol": "USDT"
        },
        "date": 1648080000,
        "dailyVolumeUSD": "14405597.15281114318190275322810628",
        "dailyTxns": "2978",
        "priceUSD": "1.000425367125232515196050747666081"
      },
      {
        "token": {
          "symbol": "USDT"
        },
        "date": 1647993600,
        "dailyVolumeUSD": "17063670.54329542390957753631439252",
        "dailyTxns": "2868",
        "priceUSD": "1.000771235868530302036110703422438"
      },
      {
        "token": {
          "symbol": "USDT"
        },
        "date": 1647907200,
        "dailyVolumeUSD": "24393941.97270551100034937561010788",
        "dailyTxns": "3517",
        "priceUSD": "0.9995210444117443526326783622381367"
      },
      {
        "token": {
          "symbol": "USDT"
        },
        "date": 1647820800,
        "dailyVolumeUSD": "12352677.78574310170227546904893234",
        "dailyTxns": "3140",
        "priceUSD": "1.00038409778073940639366324820515"
      },
      {
        "token": {
          "symbol": "USDT"
        },
        "date": 1647734400,
        "dailyVolumeUSD": "15366880.99117299919758514134191186",
        "dailyTxns": "3639",
        "priceUSD": "0.9995066634011579657887044820935141"
      },
      {
        "token": {
          "symbol": "USDT"
        },
        "date": 1647648000,
        "dailyVolumeUSD": "14334725.85740945260812329659057846",
        "dailyTxns": "3212",
        "priceUSD": "1.000199751863259488523253442075715"
      },
      {
        "token": {
          "symbol": "USDT"
        },
        "date": 1647561600,
        "dailyVolumeUSD": "16770695.46598779754982085785988212",
        "dailyTxns": "2970",
        "priceUSD": "1.001459444352103292134954010800597"
      },
      {
        "token": {
          "symbol": "USDT"
        },
        "date": 1647475200,
        "dailyVolumeUSD": "12307990.57546605681629132929295088",
        "dailyTxns": "3094",
        "priceUSD": "1.00138843676823593354870578246608"
      },
      {
        "token": {
          "symbol": "USDT"
        },
        "date": 1647388800,
        "dailyVolumeUSD": "21353740.02348026600689125151145203",
        "dailyTxns": "3584",
        "priceUSD": "1.000120247329195263218145686739977"
      },
      {
        "token": {
          "symbol": "USDT"
        },
        "date": 1647302400,
        "dailyVolumeUSD": "13223167.24423392055511860353972965",
        "dailyTxns": "3255",
        "priceUSD": "1.000906521030227091621654004660004"
      },
      {
        "token": {
          "symbol": "USDT"
        },
        "date": 1647216000,
        "dailyVolumeUSD": "12708660.75094991449952528849789902",
        "dailyTxns": "3145",
        "priceUSD": "1.000853958843558537494039499024852"
      },
      {
        "token": {
          "symbol": "USDT"
        },
        "date": 1647129600,
        "dailyVolumeUSD": "10410844.05007541422949921991263416",
        "dailyTxns": "2872",
        "priceUSD": "1.00016307173088825255412410006834"
      },
      {
        "token": {
          "symbol": "USDT"
        },
        "date": 1647043200,
        "dailyVolumeUSD": "11362286.16500659942882131628384143",
        "dailyTxns": "3022",
        "priceUSD": "1.000347800633580460852244702441567"
      },
      {
        "token": {
          "symbol": "USDT"
        },
        "date": 1646956800,
        "dailyVolumeUSD": "16765836.27824892562646483622278709",
        "dailyTxns": "3232",
        "priceUSD": "1.000095312281185714920162249355016"
      },
      {
        "token": {
          "symbol": "USDT"
        },
        "date": 1646870400,
        "dailyVolumeUSD": "14874910.38551962161551881964865012",
        "dailyTxns": "3225",
        "priceUSD": "1.00018524737434402572849527208905"
      },
      {
        "token": {
          "symbol": "USDT"
        },
        "date": 1646784000,
        "dailyVolumeUSD": "17703282.9735866474848094725185769",
        "dailyTxns": "3625",
        "priceUSD": "0.9997617141769341268176393906425795"
      },
      {
        "token": {
          "symbol": "USDT"
        },
        "date": 1646697600,
        "dailyVolumeUSD": "24669481.740974338645230435570131",
        "dailyTxns": "3413",
        "priceUSD": "0.999334306453060094563199128418312"
      },
      {
        "token": {
          "symbol": "USDT"
        },
        "date": 1646611200,
        "dailyVolumeUSD": "24684106.90900863518431782618310693",
        "dailyTxns": "3789",
        "priceUSD": "1.000002852384743930372483754594244"
      },
      {
        "token": {
          "symbol": "USDT"
        },
        "date": 1646524800,
        "dailyVolumeUSD": "16997636.4496239013465677597037629",
        "dailyTxns": "3089",
        "priceUSD": "1.000087155787258597814377747071111"
      },
      {
        "token": {
          "symbol": "USDT"
        },
        "date": 1646438400,
        "dailyVolumeUSD": "15050917.7408272509707203100381405",
        "dailyTxns": "2987",
        "priceUSD": "0.9997945922755452098595485539258434"
      },
      {
        "token": {
          "symbol": "USDT"
        },
        "date": 1646352000,
        "dailyVolumeUSD": "22734662.93257723905318293753927885",
        "dailyTxns": "3362",
        "priceUSD": "1.001185028315486620865264029297168"
      },
      {
        "token": {
          "symbol": "USDT"
        },
        "date": 1646265600,
        "dailyVolumeUSD": "19919129.27679501228469116182846094",
        "dailyTxns": "3122",
        "priceUSD": "1.00087738416420268787835545586889"
      },
      {
        "token": {
          "symbol": "USDT"
        },
        "date": 1646179200,
        "dailyVolumeUSD": "25878605.50701622839429377455981367",
        "dailyTxns": "3446",
        "priceUSD": "0.9999643549567914311483484007809317"
      },
      {
        "token": {
          "symbol": "USDT"
        },
        "date": 1646092800,
        "dailyVolumeUSD": "26826290.2679087488598638110794023",
        "dailyTxns": "3402",
        "priceUSD": "1.000027179965878657967210694671365"
      },
      {
        "token": {
          "symbol": "USDT"
        },
        "date": 1646006400,
        "dailyVolumeUSD": "26239030.75784664456357781635472389",
        "dailyTxns": "2935",
        "priceUSD": "1.001544854433698413552163078483137"
      },
      {
        "token": {
          "symbol": "USDT"
        },
        "date": 1645920000,
        "dailyVolumeUSD": "30305465.71053531197830253306410645",
        "dailyTxns": "2862",
        "priceUSD": "0.9998139478351776372470846703346013"
      },
      {
        "token": {
          "symbol": "USDT"
        },
        "date": 1645833600,
        "dailyVolumeUSD": "19693363.70398027491096038129202129",
        "dailyTxns": "2625",
        "priceUSD": "0.9998737200836086143691586497577832"
      },
      {
        "token": {
          "symbol": "USDT"
        },
        "date": 1645747200,
        "dailyVolumeUSD": "26774539.10787590626723924172142557",
        "dailyTxns": "2737",
        "priceUSD": "1.000486716170171963109332095029375"
      },
      {
        "token": {
          "symbol": "USDT"
        },
        "date": 1645660800,
        "dailyVolumeUSD": "85997386.9228875819075750106655305",
        "dailyTxns": "5879",
        "priceUSD": "0.9998379692470902621607981965323326"
      },
      {
        "token": {
          "symbol": "USDT"
        },
        "date": 1645574400,
        "dailyVolumeUSD": "18041128.48006580176919331615971594",
        "dailyTxns": "2585",
        "priceUSD": "1.000718938380908380823383878409049"
      },
      {
        "token": {
          "symbol": "USDT"
        },
        "date": 1645488000,
        "dailyVolumeUSD": "26031954.28626086661946015769786459",
        "dailyTxns": "3081",
        "priceUSD": "0.9990677011429850553075648400565722"
      },
      {
        "token": {
          "symbol": "USDT"
        },
        "date": 1645401600,
        "dailyVolumeUSD": "33970768.43415647773049982945464062",
        "dailyTxns": "2946",
        "priceUSD": "0.9993024010177418916794939073851035"
      },
      {
        "token": {
          "symbol": "USDT"
        },
        "date": 1645315200,
        "dailyVolumeUSD": "19927382.95605778131582611364955695",
        "dailyTxns": "2984",
        "priceUSD": "1.001266424276586376393232788280575"
      },
      {
        "token": {
          "symbol": "USDT"
        },
        "date": 1645228800,
        "dailyVolumeUSD": "16415148.34490925676752019699770007",
        "dailyTxns": "2733",
        "priceUSD": "1.00042093076554166575129035571918"
      },
      {
        "token": {
          "symbol": "USDT"
        },
        "date": 1645142400,
        "dailyVolumeUSD": "29412413.40454420443465911097755627",
        "dailyTxns": "3236",
        "priceUSD": "0.999425256854024543276271711028309"
      },
      {
        "token": {
          "symbol": "USDT"
        },
        "date": 1645056000,
        "dailyVolumeUSD": "30272230.69872060966365659774667388",
        "dailyTxns": "3381",
        "priceUSD": "0.9996514029626779001619533070148121"
      },
      {
        "token": {
          "symbol": "USDT"
        },
        "date": 1644969600,
        "dailyVolumeUSD": "22470219.64364756151672319349559793",
        "dailyTxns": "2978",
        "priceUSD": "1.00016461942954359351290573416336"
      },
      {
        "token": {
          "symbol": "USDT"
        },
        "date": 1644883200,
        "dailyVolumeUSD": "23382161.39551940299436221883533051",
        "dailyTxns": "3204",
        "priceUSD": "1.001058988372069770092490060073498"
      },
      {
        "token": {
          "symbol": "USDT"
        },
        "date": 1644796800,
        "dailyVolumeUSD": "22234765.99952182682773006767750622",
        "dailyTxns": "2870",
        "priceUSD": "0.9985548611144235722263564622996357"
      },
      {
        "token": {
          "symbol": "USDT"
        },
        "date": 1644710400,
        "dailyVolumeUSD": "14475332.83519081550152979722776736",
        "dailyTxns": "2742",
        "priceUSD": "1.000644021159073505453578237432252"
      },
      {
        "token": {
          "symbol": "USDT"
        },
        "date": 1644624000,
        "dailyVolumeUSD": "29878382.7144718110278220536276025",
        "dailyTxns": "3128",
        "priceUSD": "1.00027616995130504190019917204104"
      },
      {
        "token": {
          "symbol": "USDT"
        },
        "date": 1644537600,
        "dailyVolumeUSD": "30944029.61350064122951388517705649",
        "dailyTxns": "3321",
        "priceUSD": "0.9982032698477614291005723766911131"
      },
      {
        "token": {
          "symbol": "USDT"
        },
        "date": 1644451200,
        "dailyVolumeUSD": "34534210.70022872743380993519829087",
        "dailyTxns": "3300",
        "priceUSD": "0.9997611009100926921816243125052065"
      },
      {
        "token": {
          "symbol": "USDT"
        },
        "date": 1644364800,
        "dailyVolumeUSD": "20999144.48436475446229403385951347",
        "dailyTxns": "3103",
        "priceUSD": "1.000613873247246540960179994436508"
      },
      {
        "token": {
          "symbol": "USDT"
        },
        "date": 1644278400,
        "dailyVolumeUSD": "30895351.6569682887328125436886346",
        "dailyTxns": "3434",
        "priceUSD": "1.002399682338357708154280933366159"
      },
      {
        "token": {
          "symbol": "USDT"
        },
        "date": 1644192000,
        "dailyVolumeUSD": "24123419.46416353724376030258826491",
        "dailyTxns": "3079",
        "priceUSD": "1.000994505854959049408545080605311"
      },
      {
        "token": {
          "symbol": "USDT"
        },
        "date": 1644105600,
        "dailyVolumeUSD": "15578898.08210061651293924758654897",
        "dailyTxns": "2693",
        "priceUSD": "1.000140483125765925176729880087938"
      },
      {
        "token": {
          "symbol": "USDT"
        },
        "date": 1644019200,
        "dailyVolumeUSD": "18050047.59384111109273286825518515",
        "dailyTxns": "2605",
        "priceUSD": "1.000591084001095087692694569902122"
      },
      {
        "token": {
          "symbol": "USDT"
        },
        "date": 1643932800,
        "dailyVolumeUSD": "28284421.61886189424295851402494394",
        "dailyTxns": "2885",
        "priceUSD": "0.9988665128978530389276176630983948"
      },
      {
        "token": {
          "symbol": "USDT"
        },
        "date": 1643846400,
        "dailyVolumeUSD": "22985443.99752369677506293559481901",
        "dailyTxns": "2512",
        "priceUSD": "1.000615305641919778107304789114412"
      },
      {
        "token": {
          "symbol": "USDT"
        },
        "date": 1643760000,
        "dailyVolumeUSD": "27288885.40744515400513542244789262",
        "dailyTxns": "2616",
        "priceUSD": "0.9998229992085807800872278463926809"
      },
      {
        "token": {
          "symbol": "USDT"
        },
        "date": 1643673600,
        "dailyVolumeUSD": "28687895.34872502954384942294305056",
        "dailyTxns": "2480",
        "priceUSD": "0.9994998742534397802459316540019208"
      },
      {
        "token": {
          "symbol": "USDT"
        },
        "date": 1643587200,
        "dailyVolumeUSD": "21121875.24811040479557747877147205",
        "dailyTxns": "2451",
        "priceUSD": "1.000364647257456834087352779618797"
      },
      {
        "token": {
          "symbol": "USDT"
        },
        "date": 1643500800,
        "dailyVolumeUSD": "16680170.40117069070042862496067516",
        "dailyTxns": "2363",
        "priceUSD": "1.000305952859773445811618279536664"
      },
      {
        "token": {
          "symbol": "USDT"
        },
        "date": 1643414400,
        "dailyVolumeUSD": "25085227.10517159290697968908350401",
        "dailyTxns": "2698",
        "priceUSD": "0.9999563929214201384389162473829098"
      },
      {
        "token": {
          "symbol": "USDT"
        },
        "date": 1643328000,
        "dailyVolumeUSD": "41468388.62882298719815301570102625",
        "dailyTxns": "2898",
        "priceUSD": "1.002022395872612658803678472700368"
      },
      {
        "token": {
          "symbol": "USDT"
        },
        "date": 1643241600,
        "dailyVolumeUSD": "37911850.86413630163118055064689809",
        "dailyTxns": "2874",
        "priceUSD": "0.9998995681425988237611752189665281"
      },
      {
        "token": {
          "symbol": "USDT"
        },
        "date": 1643155200,
        "dailyVolumeUSD": "45225846.56823306401416380555512317",
        "dailyTxns": "3233",
        "priceUSD": "0.9984165511422967283122587265869752"
      },
      {
        "token": {
          "symbol": "USDT"
        },
        "date": 1643068800,
        "dailyVolumeUSD": "29128607.21217353089130107674471331",
        "dailyTxns": "2737",
        "priceUSD": "1.000066627725702384453024714518604"
      },
      {
        "token": {
          "symbol": "USDT"
        },
        "date": 1642982400,
        "dailyVolumeUSD": "89244771.01339802074513547424669605",
        "dailyTxns": "4392",
        "priceUSD": "0.9990308721478337088167792217254966"
      },
      {
        "token": {
          "symbol": "USDT"
        },
        "date": 1642896000,
        "dailyVolumeUSD": "35868027.11730948075769986649899768",
        "dailyTxns": "3330",
        "priceUSD": "0.9993959716370253750104571176117345"
      },
      {
        "token": {
          "symbol": "USDT"
        },
        "date": 1642809600,
        "dailyVolumeUSD": "117270017.2938422758848776531708191",
        "dailyTxns": "5665",
        "priceUSD": "1.000479594881898006400815002728384"
      },
      {
        "token": {
          "symbol": "USDT"
        },
        "date": 1642723200,
        "dailyVolumeUSD": "126600774.4898739374886357369065887",
        "dailyTxns": "5145",
        "priceUSD": "1.001836856952801529418567407454355"
      },
      {
        "token": {
          "symbol": "USDT"
        },
        "date": 1642636800,
        "dailyVolumeUSD": "29208747.92665373118509226652327438",
        "dailyTxns": "3402",
        "priceUSD": "0.9992598773784010418230979921817384"
      },
      {
        "token": {
          "symbol": "USDT"
        },
        "date": 1642550400,
        "dailyVolumeUSD": "29658251.52233693707955816926110915",
        "dailyTxns": "3375",
        "priceUSD": "1.000339237042177994576778236421149"
      },
      {
        "token": {
          "symbol": "USDT"
        },
        "date": 1642464000,
        "dailyVolumeUSD": "24052152.09870538431310456710133748",
        "dailyTxns": "3341",
        "priceUSD": "1.000084960429288745106005812510792"
      },
      {
        "token": {
          "symbol": "USDT"
        },
        "date": 1642377600,
        "dailyVolumeUSD": "33060101.70700676556604105376298901",
        "dailyTxns": "2992",
        "priceUSD": "0.9990972245099195816737509101172062"
      },
      {
        "token": {
          "symbol": "USDT"
        },
        "date": 1642291200,
        "dailyVolumeUSD": "20007234.87442648226984553748186821",
        "dailyTxns": "2628",
        "priceUSD": "0.9986872089456741922871761043248165"
      },
      {
        "token": {
          "symbol": "USDT"
        },
        "date": 1642204800,
        "dailyVolumeUSD": "19827133.46918584843123970198967249",
        "dailyTxns": "2686",
        "priceUSD": "1.00044563011908771063658522917346"
      },
      {
        "token": {
          "symbol": "USDT"
        },
        "date": 1642118400,
        "dailyVolumeUSD": "25086002.82340004971629674616556867",
        "dailyTxns": "4026",
        "priceUSD": "0.9997482400366626839584078196874925"
      },
      {
        "token": {
          "symbol": "USDT"
        },
        "date": 1642032000,
        "dailyVolumeUSD": "23293302.00150070944564341571579808",
        "dailyTxns": "2730",
        "priceUSD": "1.000512685221370476507169804408931"
      },
      {
        "token": {
          "symbol": "USDT"
        },
        "date": 1641945600,
        "dailyVolumeUSD": "27977981.40512413252785685374218183",
        "dailyTxns": "3040",
        "priceUSD": "0.9997113017903697943093229096557206"
      },
      {
        "token": {
          "symbol": "USDT"
        },
        "date": 1641859200,
        "dailyVolumeUSD": "26798889.71237172790908859543182155",
        "dailyTxns": "3051",
        "priceUSD": "0.998824557173659615717410687733715"
      },
      {
        "token": {
          "symbol": "USDT"
        },
        "date": 1641772800,
        "dailyVolumeUSD": "34477092.26056356352402038786365909",
        "dailyTxns": "2935",
        "priceUSD": "0.9993349690223371315916117334582671"
      },
      {
        "token": {
          "symbol": "USDT"
        },
        "date": 1641686400,
        "dailyVolumeUSD": "25367865.1020088022352292217289679",
        "dailyTxns": "2715",
        "priceUSD": "0.9981506695729569957845964373805037"
      },
      {
        "token": {
          "symbol": "USDT"
        },
        "date": 1641600000,
        "dailyVolumeUSD": "45487069.88164703810168720026941327",
        "dailyTxns": "3719",
        "priceUSD": "1.00056496569187695220345230266935"
      },
      {
        "token": {
          "symbol": "USDT"
        },
        "date": 1641513600,
        "dailyVolumeUSD": "70236919.69581029115716930950747392",
        "dailyTxns": "4277",
        "priceUSD": "0.9996347164719670522485592745975296"
      },
      {
        "token": {
          "symbol": "USDT"
        },
        "date": 1641427200,
        "dailyVolumeUSD": "49967896.19089107774715122572812528",
        "dailyTxns": "4638",
        "priceUSD": "1.000271962668755597841935658850005"
      },
      {
        "token": {
          "symbol": "USDT"
        },
        "date": 1641340800,
        "dailyVolumeUSD": "58385290.82484933055308978754023779",
        "dailyTxns": "4705",
        "priceUSD": "0.9997264440310921590529504325851343"
      },
      {
        "token": {
          "symbol": "USDT"
        },
        "date": 1641254400,
        "dailyVolumeUSD": "33620256.70222844702261525771007493",
        "dailyTxns": "3808",
        "priceUSD": "1.001272956919863757690409602865374"
      },
      {
        "token": {
          "symbol": "USDT"
        },
        "date": 1641168000,
        "dailyVolumeUSD": "28216181.43611624603629797186067131",
        "dailyTxns": "3615",
        "priceUSD": "0.999588134936224625019353427771003"
      },
      {
        "token": {
          "symbol": "USDT"
        },
        "date": 1641081600,
        "dailyVolumeUSD": "24534796.82319696314053546817386661",
        "dailyTxns": "3586",
        "priceUSD": "1.000201719189123867749111021036243"
      },
      {
        "token": {
          "symbol": "USDT"
        },
        "date": 1640995200,
        "dailyVolumeUSD": "23393793.99847569137451947884529513",
        "dailyTxns": "4036",
        "priceUSD": "1.001925622804604730716008829810364"
      },
      {
        "token": {
          "symbol": "USDT"
        },
        "date": 1640908800,
        "dailyVolumeUSD": "34539690.87643886055093375116721538",
        "dailyTxns": "5090",
        "priceUSD": "1.000458383498597484079220682706273"
      },
      {
        "token": {
          "symbol": "USDT"
        },
        "date": 1640822400,
        "dailyVolumeUSD": "39880824.50910647963466401477805213",
        "dailyTxns": "5377",
        "priceUSD": "1.000102119543941376783087528337364"
      },
      {
        "token": {
          "symbol": "USDT"
        },
        "date": 1640736000,
        "dailyVolumeUSD": "34662885.92806516082221435882407663",
        "dailyTxns": "4393",
        "priceUSD": "0.9990158711549705956023673973326416"
      },
      {
        "token": {
          "symbol": "USDT"
        },
        "date": 1640649600,
        "dailyVolumeUSD": "36847152.1596425287964689897656605",
        "dailyTxns": "5261",
        "priceUSD": "1.000191689090439804398789139738474"
      },
      {
        "token": {
          "symbol": "USDT"
        },
        "date": 1640563200,
        "dailyVolumeUSD": "36433056.8550607077596638265431117",
        "dailyTxns": "5628",
        "priceUSD": "1.000095918617989068709231072537306"
      },
      {
        "token": {
          "symbol": "USDT"
        },
        "date": 1640476800,
        "dailyVolumeUSD": "26418974.41258973159741894131020254",
        "dailyTxns": "4759",
        "priceUSD": "1.00004421588805777608147888842033"
      },
      {
        "token": {
          "symbol": "USDT"
        },
        "date": 1640390400,
        "dailyVolumeUSD": "24263638.81753498508977121751829526",
        "dailyTxns": "4752",
        "priceUSD": "1.001315697898489109838933817948308"
      },
      {
        "token": {
          "symbol": "USDT"
        },
        "date": 1640304000,
        "dailyVolumeUSD": "39034998.03252796989040720508621068",
        "dailyTxns": "6462",
        "priceUSD": "1.000779274609411269765758688257102"
      },
      {
        "token": {
          "symbol": "USDT"
        },
        "date": 1640217600,
        "dailyVolumeUSD": "47081231.86987532757606874489161488",
        "dailyTxns": "9182",
        "priceUSD": "1.000433336635682122591241078448512"
      },
      {
        "token": {
          "symbol": "USDT"
        },
        "date": 1640131200,
        "dailyVolumeUSD": "58902189.28283534279140107137614825",
        "dailyTxns": "7865",
        "priceUSD": "1.001992235665053663375486614541206"
      },
      {
        "token": {
          "symbol": "USDT"
        },
        "date": 1640044800,
        "dailyVolumeUSD": "25780584.98351481163937757661380668",
        "dailyTxns": "3854",
        "priceUSD": "1.001279031790225099477394631018358"
      },
      {
        "token": {
          "symbol": "USDT"
        },
        "date": 1639958400,
        "dailyVolumeUSD": "36929430.69319933035507910992213529",
        "dailyTxns": "4152",
        "priceUSD": "1.000405214842797391376760771506012"
      },
      {
        "token": {
          "symbol": "USDT"
        },
        "date": 1639872000,
        "dailyVolumeUSD": "25197427.07186963653316992441320479",
        "dailyTxns": "3884",
        "priceUSD": "1.0008421596158164908848176262445"
      },
      {
        "token": {
          "symbol": "USDT"
        },
        "date": 1639785600,
        "dailyVolumeUSD": "26054153.31824794508880656664149338",
        "dailyTxns": "3381",
        "priceUSD": "1.001392479385730376205258235981964"
      },
      {
        "token": {
          "symbol": "USDT"
        },
        "date": 1639699200,
        "dailyVolumeUSD": "41959164.46284409140826555641641413",
        "dailyTxns": "3715",
        "priceUSD": "0.9996018433215420819933972165871307"
      },
      {
        "token": {
          "symbol": "USDT"
        },
        "date": 1639612800,
        "dailyVolumeUSD": "27097058.33745435028331896868233576",
        "dailyTxns": "3493",
        "priceUSD": "0.9998353628449429897547101545070064"
      },
      {
        "token": {
          "symbol": "USDT"
        },
        "date": 1639526400,
        "dailyVolumeUSD": "46138635.11562049617511640735175663",
        "dailyTxns": "4500",
        "priceUSD": "0.9996936015919535002503914376477408"
      },
      {
        "token": {
          "symbol": "USDT"
        },
        "date": 1639440000,
        "dailyVolumeUSD": "53247666.44047575521551396514928082",
        "dailyTxns": "4116",
        "priceUSD": "0.9995661444974273388169078646843793"
      },
      {
        "token": {
          "symbol": "USDT"
        },
        "date": 1639353600,
        "dailyVolumeUSD": "46288044.99587775276155537596205727",
        "dailyTxns": "3939",
        "priceUSD": "1.001028776935006751532205271726916"
      },
      {
        "token": {
          "symbol": "USDT"
        },
        "date": 1639267200,
        "dailyVolumeUSD": "22709985.75977627967922782089016458",
        "dailyTxns": "3511",
        "priceUSD": "0.9995280758805424241496133836372347"
      },
      {
        "token": {
          "symbol": "USDT"
        },
        "date": 1639180800,
        "dailyVolumeUSD": "40116788.98998529310079176315217346",
        "dailyTxns": "4035",
        "priceUSD": "1.000395876490154029540710211760506"
      },
      {
        "token": {
          "symbol": "USDT"
        },
        "date": 1639094400,
        "dailyVolumeUSD": "57171509.33453435946614159548242231",
        "dailyTxns": "4943",
        "priceUSD": "1.00134617009282608237027348709025"
      },
      {
        "token": {
          "symbol": "USDT"
        },
        "date": 1639008000,
        "dailyVolumeUSD": "52731551.63968309128011419300701857",
        "dailyTxns": "4890",
        "priceUSD": "1.00062814200414334876022773060978"
      },
      {
        "token": {
          "symbol": "USDT"
        },
        "date": 1638921600,
        "dailyVolumeUSD": "50760465.03564475325301543691541734",
        "dailyTxns": "3669",
        "priceUSD": "1.000180376336295280659561718464577"
      },
      {
        "token": {
          "symbol": "USDT"
        },
        "date": 1638835200,
        "dailyVolumeUSD": "46851350.14913283112029050537771232",
        "dailyTxns": "4017",
        "priceUSD": "1.000880911048601305328108221184342"
      },
      {
        "token": {
          "symbol": "USDT"
        },
        "date": 1638748800,
        "dailyVolumeUSD": "71884157.44828348229228192816200577",
        "dailyTxns": "5151",
        "priceUSD": "1.000450517961749667280361991574986"
      },
      {
        "token": {
          "symbol": "USDT"
        },
        "date": 1638662400,
        "dailyVolumeUSD": "50150094.86329729425447429504333216",
        "dailyTxns": "4228",
        "priceUSD": "1.000741606654988804673850611716034"
      },
      {
        "token": {
          "symbol": "USDT"
        },
        "date": 1638576000,
        "dailyVolumeUSD": "147992543.0757675275325304157606254",
        "dailyTxns": "5822",
        "priceUSD": "1.000462045595160377245685987160801"
      },
      {
        "token": {
          "symbol": "USDT"
        },
        "date": 1638489600,
        "dailyVolumeUSD": "70608198.3875595970009387692249421",
        "dailyTxns": "5403",
        "priceUSD": "0.9999804233842945732838705291153751"
      },
      {
        "token": {
          "symbol": "USDT"
        },
        "date": 1638403200,
        "dailyVolumeUSD": "80473564.74508356705137400922893221",
        "dailyTxns": "7241",
        "priceUSD": "1.000141412434268670010162379142753"
      },
      {
        "token": {
          "symbol": "USDT"
        },
        "date": 1638316800,
        "dailyVolumeUSD": "50904636.58276312482039233025139887",
        "dailyTxns": "4640",
        "priceUSD": "1.000274795791740249281259132541106"
      },
      {
        "token": {
          "symbol": "USDT"
        },
        "date": 1638230400,
        "dailyVolumeUSD": "81447511.30010861667342283695900852",
        "dailyTxns": "5094",
        "priceUSD": "1.000414774628444999476688564006175"
      },
      {
        "token": {
          "symbol": "USDT"
        },
        "date": 1638144000,
        "dailyVolumeUSD": "54671632.73846005839218484075484666",
        "dailyTxns": "5199",
        "priceUSD": "1.001312757787269726744247089197931"
      },
      {
        "token": {
          "symbol": "USDT"
        },
        "date": 1638057600,
        "dailyVolumeUSD": "55652690.01270125730852913676332614",
        "dailyTxns": "4640",
        "priceUSD": "1.00070442044580125701143704743113"
      },
      {
        "token": {
          "symbol": "USDT"
        },
        "date": 1637971200,
        "dailyVolumeUSD": "38370367.09715886318167614229654673",
        "dailyTxns": "4604",
        "priceUSD": "1.000541437311465899745233493856692"
      },
      {
        "token": {
          "symbol": "USDT"
        },
        "date": 1637884800,
        "dailyVolumeUSD": "85435772.42945545425715126853527098",
        "dailyTxns": "5780",
        "priceUSD": "1.000285301262672747075196640980128"
      },
      {
        "token": {
          "symbol": "USDT"
        },
        "date": 1637798400,
        "dailyVolumeUSD": "57605583.96675580698528971532546304",
        "dailyTxns": "5349",
        "priceUSD": "1.000421973500305615912268948737096"
      },
      {
        "token": {
          "symbol": "USDT"
        },
        "date": 1637712000,
        "dailyVolumeUSD": "60704521.85291603702377404939203341",
        "dailyTxns": "4935",
        "priceUSD": "0.998823817921555572173042877797762"
      },
      {
        "token": {
          "symbol": "USDT"
        },
        "date": 1637625600,
        "dailyVolumeUSD": "57533380.50078691948520560643809099",
        "dailyTxns": "4675",
        "priceUSD": "1.000099619717585490068933879990888"
      },
      {
        "token": {
          "symbol": "USDT"
        },
        "date": 1637539200,
        "dailyVolumeUSD": "63211214.18204219505557708498217357",
        "dailyTxns": "4242",
        "priceUSD": "0.9996005742052965688282558174200722"
      },
      {
        "token": {
          "symbol": "USDT"
        },
        "date": 1637452800,
        "dailyVolumeUSD": "51722136.54988406108284417951544725",
        "dailyTxns": "4674",
        "priceUSD": "1.001317486176670336399132827373896"
      },
      {
        "token": {
          "symbol": "USDT"
        },
        "date": 1637366400,
        "dailyVolumeUSD": "46476536.32356245549526926154712448",
        "dailyTxns": "4607",
        "priceUSD": "1.000097068973404651836052203012812"
      },
      {
        "token": {
          "symbol": "USDT"
        },
        "date": 1637280000,
        "dailyVolumeUSD": "59960141.59461305658993709764973508",
        "dailyTxns": "4978",
        "priceUSD": "0.9989147095310007636264880934876333"
      },
      {
        "token": {
          "symbol": "USDT"
        },
        "date": 1637193600,
        "dailyVolumeUSD": "110568666.0787078586919440777126641",
        "dailyTxns": "6107",
        "priceUSD": "0.9995265897465011269690260578311811"
      },
      {
        "token": {
          "symbol": "USDT"
        },
        "date": 1637107200,
        "dailyVolumeUSD": "75480132.96714741757571789655807983",
        "dailyTxns": "5478",
        "priceUSD": "0.9987620482143533494223406743042841"
      },
      {
        "token": {
          "symbol": "USDT"
        },
        "date": 1637020800,
        "dailyVolumeUSD": "92689577.01567050825340985439882856",
        "dailyTxns": "5727",
        "priceUSD": "1.000010382123627043684595577212841"
      },
      {
        "token": {
          "symbol": "USDT"
        },
        "date": 1636934400,
        "dailyVolumeUSD": "66403650.98358643585963464395037744",
        "dailyTxns": "5634",
        "priceUSD": "0.9986685628144513167654881307585357"
      },
      {
        "token": {
          "symbol": "USDT"
        },
        "date": 1636848000,
        "dailyVolumeUSD": "73555008.62474184896934771557470081",
        "dailyTxns": "5992",
        "priceUSD": "0.9992001751443325743247646546641819"
      },
      {
        "token": {
          "symbol": "USDT"
        },
        "date": 1636761600,
        "dailyVolumeUSD": "92474919.7505964833396312202704507",
        "dailyTxns": "5685",
        "priceUSD": "0.9983089291863839447743316936900889"
      },
      {
        "token": {
          "symbol": "USDT"
        },
        "date": 1636675200,
        "dailyVolumeUSD": "96781097.99159155736114104406675713",
        "dailyTxns": "6104",
        "priceUSD": "0.9985528770207570417837449621343738"
      },
      {
        "token": {
          "symbol": "USDT"
        },
        "date": 1636588800,
        "dailyVolumeUSD": "82140860.71679606253549319422606988",
        "dailyTxns": "6354",
        "priceUSD": "1.000173151390060597713560590970011"
      },
      {
        "token": {
          "symbol": "USDT"
        },
        "date": 1636502400,
        "dailyVolumeUSD": "75435209.13995431792881359185621656",
        "dailyTxns": "5817",
        "priceUSD": "1.003282355002366399600263524800871"
      },
      {
        "token": {
          "symbol": "USDT"
        },
        "date": 1636416000,
        "dailyVolumeUSD": "54123481.57968028159941284488125083",
        "dailyTxns": "4712",
        "priceUSD": "0.9985291155185403574218341585340042"
      },
      {
        "token": {
          "symbol": "USDT"
        },
        "date": 1636329600,
        "dailyVolumeUSD": "52473694.96896725997344334669972879",
        "dailyTxns": "5296",
        "priceUSD": "0.9985590702964369716549159772939697"
      },
      {
        "token": {
          "symbol": "USDT"
        },
        "date": 1636243200,
        "dailyVolumeUSD": "47213498.25950097870876503403630951",
        "dailyTxns": "6055",
        "priceUSD": "0.9993559505420837699226240047062747"
      },
      {
        "token": {
          "symbol": "USDT"
        },
        "date": 1636156800,
        "dailyVolumeUSD": "47048632.402962306624794846034324",
        "dailyTxns": "5533",
        "priceUSD": "1.00063431515411701591864732311194"
      },
      {
        "token": {
          "symbol": "USDT"
        },
        "date": 1636070400,
        "dailyVolumeUSD": "55821235.76650315975986901818895957",
        "dailyTxns": "5298",
        "priceUSD": "1.000751390873686969724728892451101"
      },
      {
        "token": {
          "symbol": "USDT"
        },
        "date": 1635984000,
        "dailyVolumeUSD": "58818377.44921341454672489711726092",
        "dailyTxns": "5743",
        "priceUSD": "1.000079818359694824807973775378384"
      },
      {
        "token": {
          "symbol": "USDT"
        },
        "date": 1635897600,
        "dailyVolumeUSD": "74767589.36299977559009419295645942",
        "dailyTxns": "6761",
        "priceUSD": "1.00138465691282037512504729537774"
      },
      {
        "token": {
          "symbol": "USDT"
        },
        "date": 1635811200,
        "dailyVolumeUSD": "68756863.53810547961357314037058135",
        "dailyTxns": "5965",
        "priceUSD": "0.9990132946695254725916293516786635"
      },
      {
        "token": {
          "symbol": "USDT"
        },
        "date": 1635724800,
        "dailyVolumeUSD": "59004587.14982935134739505053427809",
        "dailyTxns": "5566",
        "priceUSD": "0.9974355536146343192930781506682512"
      },
      {
        "token": {
          "symbol": "USDT"
        },
        "date": 1635638400,
        "dailyVolumeUSD": "67883422.18256713745577371850796909",
        "dailyTxns": "6533",
        "priceUSD": "1.001167589867011799674304948793901"
      },
      {
        "token": {
          "symbol": "USDT"
        },
        "date": 1635552000,
        "dailyVolumeUSD": "81949107.57777288203924985394019083",
        "dailyTxns": "7202",
        "priceUSD": "0.9971758649950396100144822764763771"
      },
      {
        "token": {
          "symbol": "USDT"
        },
        "date": 1635465600,
        "dailyVolumeUSD": "86592124.66064114604327435192151305",
        "dailyTxns": "6393",
        "priceUSD": "0.9966362777253489039970582739321843"
      },
      {
        "token": {
          "symbol": "USDT"
        },
        "date": 1635379200,
        "dailyVolumeUSD": "71849907.88240997383489140258683109",
        "dailyTxns": "5678",
        "priceUSD": "1.000316190500008599221576532386405"
      },
      {
        "token": {
          "symbol": "USDT"
        },
        "date": 1635292800,
        "dailyVolumeUSD": "71415972.31332515716696984072928837",
        "dailyTxns": "5884",
        "priceUSD": "1.001499996490438312395216872610354"
      },
      {
        "token": {
          "symbol": "USDT"
        },
        "date": 1635206400,
        "dailyVolumeUSD": "62580072.65894208017255380681927227",
        "dailyTxns": "5807",
        "priceUSD": "0.9989035563561059024553866358492857"
      },
      {
        "token": {
          "symbol": "USDT"
        },
        "date": 1635120000,
        "dailyVolumeUSD": "37994089.38521258678743320569618386",
        "dailyTxns": "5970",
        "priceUSD": "1.000407773127715387854350017058281"
      },
      {
        "token": {
          "symbol": "USDT"
        },
        "date": 1635033600,
        "dailyVolumeUSD": "35691819.16661540065890388539940467",
        "dailyTxns": "5740",
        "priceUSD": "1.001755139852917792265337047703005"
      },
      {
        "token": {
          "symbol": "USDT"
        },
        "date": 1634947200,
        "dailyVolumeUSD": "30060547.51010025836395171724043973",
        "dailyTxns": "5210",
        "priceUSD": "0.9994335281251379829936995867743535"
      },
      {
        "token": {
          "symbol": "USDT"
        },
        "date": 1634860800,
        "dailyVolumeUSD": "35123993.50270044431743502624695503",
        "dailyTxns": "5497",
        "priceUSD": "1.000028714442455274638152741364021"
      },
      {
        "token": {
          "symbol": "USDT"
        },
        "date": 1634774400,
        "dailyVolumeUSD": "53924278.31938344834334372801701893",
        "dailyTxns": "5468",
        "priceUSD": "1.000375123562475576247416182616151"
      },
      {
        "token": {
          "symbol": "USDT"
        },
        "date": 1634688000,
        "dailyVolumeUSD": "35587344.10838996980918502478120575",
        "dailyTxns": "5768",
        "priceUSD": "1.000470855012938950157124334842776"
      },
      {
        "token": {
          "symbol": "USDT"
        },
        "date": 1634601600,
        "dailyVolumeUSD": "38723137.84121583858020596755568682",
        "dailyTxns": "6096",
        "priceUSD": "0.9981145416422593942625487806269194"
      },
      {
        "token": {
          "symbol": "USDT"
        },
        "date": 1634515200,
        "dailyVolumeUSD": "38620170.76974765255645447850761863",
        "dailyTxns": "5366",
        "priceUSD": "0.9984425834928964945636369827875049"
      },
      {
        "token": {
          "symbol": "USDT"
        },
        "date": 1634428800,
        "dailyVolumeUSD": "32436865.46991529032548232344375984",
        "dailyTxns": "5306",
        "priceUSD": "1.000419412240009100703658883912233"
      },
      {
        "token": {
          "symbol": "USDT"
        },
        "date": 1634342400,
        "dailyVolumeUSD": "34696206.72438781267708343990609908",
        "dailyTxns": "5563",
        "priceUSD": "1.000645015714813097919834475278506"
      },
      {
        "token": {
          "symbol": "USDT"
        },
        "date": 1634256000,
        "dailyVolumeUSD": "46462029.42515831721107745296917105",
        "dailyTxns": "5194",
        "priceUSD": "0.9992386549397456106351576425882263"
      },
      {
        "token": {
          "symbol": "USDT"
        },
        "date": 1634169600,
        "dailyVolumeUSD": "47306621.18422680280924039257744663",
        "dailyTxns": "4854",
        "priceUSD": "0.9994857036530850407603515982564256"
      },
      {
        "token": {
          "symbol": "USDT"
        },
        "date": 1634083200,
        "dailyVolumeUSD": "39834306.45778024470104356749267761",
        "dailyTxns": "5222",
        "priceUSD": "1.000264001614363046103184844723502"
      },
      {
        "token": {
          "symbol": "USDT"
        },
        "date": 1633996800,
        "dailyVolumeUSD": "35465940.01910357728932768589962017",
        "dailyTxns": "5331",
        "priceUSD": "0.999522527830542580154335557131687"
      },
      {
        "token": {
          "symbol": "USDT"
        },
        "date": 1633910400,
        "dailyVolumeUSD": "41763151.78734934216658895711169813",
        "dailyTxns": "4643",
        "priceUSD": "0.9999279817883628736520866054542371"
      },
      {
        "token": {
          "symbol": "USDT"
        },
        "date": 1633824000,
        "dailyVolumeUSD": "34161995.61387389783514686511014524",
        "dailyTxns": "4626",
        "priceUSD": "1.000097657106681712705902874915563"
      },
      {
        "token": {
          "symbol": "USDT"
        },
        "date": 1633737600,
        "dailyVolumeUSD": "27471924.26603522527948345066860262",
        "dailyTxns": "4342",
        "priceUSD": "0.9990181236362874027250188376284652"
      },
      {
        "token": {
          "symbol": "USDT"
        },
        "date": 1633651200,
        "dailyVolumeUSD": "31187280.05797431424492322147055118",
        "dailyTxns": "4059",
        "priceUSD": "0.9993645166912416594488759047774888"
      },
      {
        "token": {
          "symbol": "USDT"
        },
        "date": 1633564800,
        "dailyVolumeUSD": "59307874.49183282432399409131236052",
        "dailyTxns": "4955",
        "priceUSD": "0.9984487303625748787044578037507411"
      },
      {
        "token": {
          "symbol": "USDT"
        },
        "date": 1633478400,
        "dailyVolumeUSD": "48704130.97422196884652889240833504",
        "dailyTxns": "4345",
        "priceUSD": "1.000392482977320330644105065272486"
      },
      {
        "token": {
          "symbol": "USDT"
        },
        "date": 1633392000,
        "dailyVolumeUSD": "37284572.22476398167818619728834517",
        "dailyTxns": "4479",
        "priceUSD": "0.9996550679365337173611773984741912"
      },
      {
        "token": {
          "symbol": "USDT"
        },
        "date": 1633305600,
        "dailyVolumeUSD": "36703732.10026485679491450690305441",
        "dailyTxns": "4695",
        "priceUSD": "1.001276918995159114432623372876889"
      },
      {
        "token": {
          "symbol": "USDT"
        },
        "date": 1633219200,
        "dailyVolumeUSD": "27308107.92497910633601246707346979",
        "dailyTxns": "4576",
        "priceUSD": "0.9975244248166162894964314661889967"
      },
      {
        "token": {
          "symbol": "USDT"
        },
        "date": 1633132800,
        "dailyVolumeUSD": "29946133.60027019684694297521000903",
        "dailyTxns": "4993",
        "priceUSD": "1.001255906622808234243805682658484"
      },
      {
        "token": {
          "symbol": "USDT"
        },
        "date": 1633046400,
        "dailyVolumeUSD": "35412639.36202162797520282846902299",
        "dailyTxns": "4672",
        "priceUSD": "1.001116283723953659363083158795718"
      },
      {
        "token": {
          "symbol": "USDT"
        },
        "date": 1632960000,
        "dailyVolumeUSD": "34116573.09305822253218937311774356",
        "dailyTxns": "5173",
        "priceUSD": "0.9996673693567192384270441193648952"
      },
      {
        "token": {
          "symbol": "USDT"
        },
        "date": 1632873600,
        "dailyVolumeUSD": "34028379.37000750305908687551418211",
        "dailyTxns": "5410",
        "priceUSD": "1.000560786024895133749123184587556"
      },
      {
        "token": {
          "symbol": "USDT"
        },
        "date": 1632787200,
        "dailyVolumeUSD": "37310152.57772841513539675950945329",
        "dailyTxns": "5029",
        "priceUSD": "1.000397280613373134723237934525181"
      },
      {
        "token": {
          "symbol": "USDT"
        },
        "date": 1632700800,
        "dailyVolumeUSD": "34485270.65815525386973503196025617",
        "dailyTxns": "4693",
        "priceUSD": "0.9998732140758930956088006233748996"
      },
      {
        "token": {
          "symbol": "USDT"
        },
        "date": 1632614400,
        "dailyVolumeUSD": "47106020.83357434395528933883137948",
        "dailyTxns": "5535",
        "priceUSD": "1.000672301719634884557105218510849"
      },
      {
        "token": {
          "symbol": "USDT"
        },
        "date": 1632528000,
        "dailyVolumeUSD": "34632081.16504209872103980881040193",
        "dailyTxns": "5223",
        "priceUSD": "1.000209634356521627031997378153676"
      },
      {
        "token": {
          "symbol": "USDT"
        },
        "date": 1632441600,
        "dailyVolumeUSD": "57120323.1886624186865792801248623",
        "dailyTxns": "5957",
        "priceUSD": "1.000555004189672500558476470915218"
      },
      {
        "token": {
          "symbol": "USDT"
        },
        "date": 1632355200,
        "dailyVolumeUSD": "35757455.37568540845478367202306009",
        "dailyTxns": "6062",
        "priceUSD": "0.9978729602372720819494439779123568"
      },
      {
        "token": {
          "symbol": "USDT"
        },
        "date": 1632268800,
        "dailyVolumeUSD": "48867194.2477877712871190757867627",
        "dailyTxns": "6275",
        "priceUSD": "1.000033758737105832585928242598366"
      },
      {
        "token": {
          "symbol": "USDT"
        },
        "date": 1632182400,
        "dailyVolumeUSD": "69299617.11326220582067074649567764",
        "dailyTxns": "6146",
        "priceUSD": "1.000152091629093088140598279607696"
      },
      {
        "token": {
          "symbol": "USDT"
        },
        "date": 1632096000,
        "dailyVolumeUSD": "78245206.37109169108512091241495095",
        "dailyTxns": "7011",
        "priceUSD": "1.00001523113347239395558717375609"
      },
      {
        "token": {
          "symbol": "USDT"
        },
        "date": 1632009600,
        "dailyVolumeUSD": "33686343.45429487686023608698442101",
        "dailyTxns": "5746",
        "priceUSD": "1.000137422074500553021351684279552"
      },
      {
        "token": {
          "symbol": "USDT"
        },
        "date": 1631923200,
        "dailyVolumeUSD": "32247559.18853399004734355140311812",
        "dailyTxns": "5572",
        "priceUSD": "0.9998796040645232144112302087125051"
      },
      {
        "token": {
          "symbol": "USDT"
        },
        "date": 1631836800,
        "dailyVolumeUSD": "35717720.65742676957655672678219737",
        "dailyTxns": "5273",
        "priceUSD": "1.000883221144124720383947360245476"
      },
      {
        "token": {
          "symbol": "USDT"
        },
        "date": 1631750400,
        "dailyVolumeUSD": "46011690.21703187343755483421029584",
        "dailyTxns": "6826",
        "priceUSD": "0.9996545213663168870477837573612176"
      },
      {
        "token": {
          "symbol": "USDT"
        },
        "date": 1631664000,
        "dailyVolumeUSD": "35167928.18538456852787745567657488",
        "dailyTxns": "6147",
        "priceUSD": "0.999529297978223478298865551812191"
      },
      {
        "token": {
          "symbol": "USDT"
        },
        "date": 1631577600,
        "dailyVolumeUSD": "49511285.03591621807840209957790102",
        "dailyTxns": "6407",
        "priceUSD": "0.9998363617013282793761239898321388"
      },
      {
        "token": {
          "symbol": "USDT"
        },
        "date": 1631491200,
        "dailyVolumeUSD": "59734504.23429520736403831845724211",
        "dailyTxns": "7032",
        "priceUSD": "1.000179477139115745984333286542293"
      },
      {
        "token": {
          "symbol": "USDT"
        },
        "date": 1631404800,
        "dailyVolumeUSD": "35313388.63433277589290695212948798",
        "dailyTxns": "6102",
        "priceUSD": "0.999614056589249023244075358033415"
      },
      {
        "token": {
          "symbol": "USDT"
        },
        "date": 1631318400,
        "dailyVolumeUSD": "37829162.50640029135277144270740213",
        "dailyTxns": "6068",
        "priceUSD": "0.999144439682053207749082879928804"
      },
      {
        "token": {
          "symbol": "USDT"
        },
        "date": 1631232000,
        "dailyVolumeUSD": "64436098.64894780900215537788111753",
        "dailyTxns": "7017",
        "priceUSD": "1.000364376735099792847522100220104"
      },
      {
        "token": {
          "symbol": "USDT"
        },
        "date": 1631145600,
        "dailyVolumeUSD": "47115089.39970588097692790436822588",
        "dailyTxns": "5193",
        "priceUSD": "0.9984897719852196522134989276617317"
      },
      {
        "token": {
          "symbol": "USDT"
        },
        "date": 1631059200,
        "dailyVolumeUSD": "77614136.23129679369577240524767738",
        "dailyTxns": "5777",
        "priceUSD": "1.000060085719884501299067801658966"
      },
      {
        "token": {
          "symbol": "USDT"
        },
        "date": 1630972800,
        "dailyVolumeUSD": "129013656.0028073573772435908254991",
        "dailyTxns": "7151",
        "priceUSD": "0.9991396650228778090468898647270199"
      },
      {
        "token": {
          "symbol": "USDT"
        },
        "date": 1630886400,
        "dailyVolumeUSD": "39737130.38894425258637961778118743",
        "dailyTxns": "5583",
        "priceUSD": "1.00216669445778656421451807654478"
      },
      {
        "token": {
          "symbol": "USDT"
        },
        "date": 1630800000,
        "dailyVolumeUSD": "32223210.15735511820752165397389755",
        "dailyTxns": "4620",
        "priceUSD": "1.000846398057405544914048056086584"
      },
      {
        "token": {
          "symbol": "USDT"
        },
        "date": 1630713600,
        "dailyVolumeUSD": "34286740.73118185887489375594494463",
        "dailyTxns": "4750",
        "priceUSD": "0.9996471609761651135205402882124962"
      },
      {
        "token": {
          "symbol": "USDT"
        },
        "date": 1630627200,
        "dailyVolumeUSD": "46064996.03978496101200739483547677",
        "dailyTxns": "4750",
        "priceUSD": "0.999679516176241586281567771129976"
      },
      {
        "token": {
          "symbol": "USDT"
        },
        "date": 1630540800,
        "dailyVolumeUSD": "44636191.11595533187905768171113428",
        "dailyTxns": "5492",
        "priceUSD": "1.000390822619513423580499826274913"
      },
      {
        "token": {
          "symbol": "USDT"
        },
        "date": 1630454400,
        "dailyVolumeUSD": "63213449.71844712898127180827245303",
        "dailyTxns": "5681",
        "priceUSD": "0.9988902908655093093017961792736203"
      },
      {
        "token": {
          "symbol": "USDT"
        },
        "date": 1630368000,
        "dailyVolumeUSD": "54074067.99007141416057846082486391",
        "dailyTxns": "6170",
        "priceUSD": "1.000904931622463011452443030701853"
      },
      {
        "token": {
          "symbol": "USDT"
        },
        "date": 1630281600,
        "dailyVolumeUSD": "45865529.97858282002068787254910151",
        "dailyTxns": "6604",
        "priceUSD": "1.000275773409163672772988134361649"
      },
      {
        "token": {
          "symbol": "USDT"
        },
        "date": 1630195200,
        "dailyVolumeUSD": "33760276.86675194656741428366445355",
        "dailyTxns": "6283",
        "priceUSD": "1.000318108336649703489582831867994"
      },
      {
        "token": {
          "symbol": "USDT"
        },
        "date": 1630108800,
        "dailyVolumeUSD": "35890210.59823510628423335189736592",
        "dailyTxns": "6913",
        "priceUSD": "0.9984002843648858564570183469409087"
      },
      {
        "token": {
          "symbol": "USDT"
        },
        "date": 1630022400,
        "dailyVolumeUSD": "54895834.25448060222813467425185281",
        "dailyTxns": "8010",
        "priceUSD": "0.9996975094137505765966951452509368"
      },
      {
        "token": {
          "symbol": "USDT"
        },
        "date": 1629936000,
        "dailyVolumeUSD": "58955773.58621630766782326953309396",
        "dailyTxns": "9279",
        "priceUSD": "0.9995045363787386805016879328074239"
      },
      {
        "token": {
          "symbol": "USDT"
        },
        "date": 1629849600,
        "dailyVolumeUSD": "57533662.45082675560019839669764171",
        "dailyTxns": "8566",
        "priceUSD": "0.99963445945256213999861971555014"
      },
      {
        "token": {
          "symbol": "USDT"
        },
        "date": 1629763200,
        "dailyVolumeUSD": "78144078.33172104830752788415817551",
        "dailyTxns": "9536",
        "priceUSD": "0.998940044003933859224146992349322"
      },
      {
        "token": {
          "symbol": "USDT"
        },
        "date": 1629676800,
        "dailyVolumeUSD": "50170637.7058789214274735976675268",
        "dailyTxns": "9443",
        "priceUSD": "1.001506643279573715740609656534681"
      },
      {
        "token": {
          "symbol": "USDT"
        },
        "date": 1629590400,
        "dailyVolumeUSD": "32733190.08865422556335443484650576",
        "dailyTxns": "8711",
        "priceUSD": "1.000051683014675955089263296417291"
      },
      {
        "token": {
          "symbol": "USDT"
        },
        "date": 1629504000,
        "dailyVolumeUSD": "34736820.68405544334947994747590528",
        "dailyTxns": "8693",
        "priceUSD": "0.9999894603471313083354427433798569"
      },
      {
        "token": {
          "symbol": "USDT"
        },
        "date": 1629417600,
        "dailyVolumeUSD": "49802638.09472211845022238085257813",
        "dailyTxns": "9340",
        "priceUSD": "0.9999882143526399369391325833827685"
      },
      {
        "token": {
          "symbol": "USDT"
        },
        "date": 1629331200,
        "dailyVolumeUSD": "47521324.86727964262816738497619225",
        "dailyTxns": "9736",
        "priceUSD": "0.999834888872236799675073029658957"
      },
      {
        "token": {
          "symbol": "USDT"
        },
        "date": 1629244800,
        "dailyVolumeUSD": "62370569.54771246907916662351448238",
        "dailyTxns": "10166",
        "priceUSD": "1.000043419437386879652001360689237"
      },
      {
        "token": {
          "symbol": "USDT"
        },
        "date": 1629158400,
        "dailyVolumeUSD": "62802640.93873435797292614544572591",
        "dailyTxns": "8850",
        "priceUSD": "0.9988874517700103380691435314806652"
      },
      {
        "token": {
          "symbol": "USDT"
        },
        "date": 1629072000,
        "dailyVolumeUSD": "52218179.51453175969897015277062579",
        "dailyTxns": "9049",
        "priceUSD": "0.9998987671463438190848253026776622"
      },
      {
        "token": {
          "symbol": "USDT"
        },
        "date": 1628985600,
        "dailyVolumeUSD": "39079174.59841070152497419572741052",
        "dailyTxns": "6678",
        "priceUSD": "0.9986087467539743357613207389489644"
      },
      {
        "token": {
          "symbol": "USDT"
        },
        "date": 1628899200,
        "dailyVolumeUSD": "35786000.64955785594756497879110939",
        "dailyTxns": "6935",
        "priceUSD": "1.000499056590154275879620262259036"
      },
      {
        "token": {
          "symbol": "USDT"
        },
        "date": 1628812800,
        "dailyVolumeUSD": "46671493.49470897040735763889649731",
        "dailyTxns": "7630",
        "priceUSD": "1.001300557256763641819609519283151"
      },
      {
        "token": {
          "symbol": "USDT"
        },
        "date": 1628726400,
        "dailyVolumeUSD": "52573495.86803581843208170967580216",
        "dailyTxns": "7256",
        "priceUSD": "1.000192828128225580162940296994474"
      },
      {
        "token": {
          "symbol": "USDT"
        },
        "date": 1628640000,
        "dailyVolumeUSD": "55576025.04067768060223368617467761",
        "dailyTxns": "8121",
        "priceUSD": "0.9996161507755852533541910843480544"
      },
      {
        "token": {
          "symbol": "USDT"
        },
        "date": 1628553600,
        "dailyVolumeUSD": "57216059.37262103652363222698315504",
        "dailyTxns": "9234",
        "priceUSD": "0.9988079764411301398891909762485174"
      },
      {
        "token": {
          "symbol": "USDT"
        },
        "date": 1628467200,
        "dailyVolumeUSD": "56509534.64941658153965620411431042",
        "dailyTxns": "6614",
        "priceUSD": "1.000092178197484773817625583732055"
      },
      {
        "token": {
          "symbol": "USDT"
        },
        "date": 1628380800,
        "dailyVolumeUSD": "54014983.83575222533945327982057251",
        "dailyTxns": "6968",
        "priceUSD": "0.9999506449996155515145242874099904"
      },
      {
        "token": {
          "symbol": "USDT"
        },
        "date": 1628294400,
        "dailyVolumeUSD": "56000377.07843134492289002993764043",
        "dailyTxns": "6826",
        "priceUSD": "0.9999979053206811919356015823903545"
      },
      {
        "token": {
          "symbol": "USDT"
        },
        "date": 1628208000,
        "dailyVolumeUSD": "45466344.79826435069466957103901681",
        "dailyTxns": "6946",
        "priceUSD": "1.000027928978088383244962536896805"
      },
      {
        "token": {
          "symbol": "USDT"
        },
        "date": 1628121600,
        "dailyVolumeUSD": "57831051.67199022030623099766846365",
        "dailyTxns": "6876",
        "priceUSD": "0.9999403384983790617348771367876546"
      },
      {
        "token": {
          "symbol": "USDT"
        },
        "date": 1628035200,
        "dailyVolumeUSD": "47226543.58395964899787513269908516",
        "dailyTxns": "7456",
        "priceUSD": "0.9991094667212601674533100395493772"
      },
      {
        "token": {
          "symbol": "USDT"
        },
        "date": 1627948800,
        "dailyVolumeUSD": "44321145.9476632666880461332799883",
        "dailyTxns": "7613",
        "priceUSD": "0.9989021917925304636711830347025585"
      },
      {
        "token": {
          "symbol": "USDT"
        },
        "date": 1627862400,
        "dailyVolumeUSD": "43562939.77346273890069000548187564",
        "dailyTxns": "7792",
        "priceUSD": "0.9998509704488273146220539224290264"
      },
      {
        "token": {
          "symbol": "USDT"
        },
        "date": 1627776000,
        "dailyVolumeUSD": "47512646.89806619317197284063573736",
        "dailyTxns": "8999",
        "priceUSD": "1.000530555402261876763124430706001"
      },
      {
        "token": {
          "symbol": "USDT"
        },
        "date": 1627689600,
        "dailyVolumeUSD": "35575425.56887097317693620416002705",
        "dailyTxns": "9464",
        "priceUSD": "1.001017435451434346890502256654275"
      },
      {
        "token": {
          "symbol": "USDT"
        },
        "date": 1627603200,
        "dailyVolumeUSD": "46174227.21524313656519806366367705",
        "dailyTxns": "9565",
        "priceUSD": "1.000412211962435645474188980226931"
      },
      {
        "token": {
          "symbol": "USDT"
        },
        "date": 1627516800,
        "dailyVolumeUSD": "32338962.09514903717722638510231067",
        "dailyTxns": "9645",
        "priceUSD": "0.9998777415189137454494181674925018"
      },
      {
        "token": {
          "symbol": "USDT"
        },
        "date": 1627430400,
        "dailyVolumeUSD": "43401650.53672930194509869587182591",
        "dailyTxns": "8358",
        "priceUSD": "0.9996618146220687120528594547406684"
      },
      {
        "token": {
          "symbol": "USDT"
        },
        "date": 1627344000,
        "dailyVolumeUSD": "44333180.20943723799146173365083258",
        "dailyTxns": "8088",
        "priceUSD": "0.9999339531535176376654701630833546"
      },
      {
        "token": {
          "symbol": "USDT"
        },
        "date": 1627257600,
        "dailyVolumeUSD": "90335275.0489254387218516146724323",
        "dailyTxns": "12145",
        "priceUSD": "1.000181357016167917017077716708965"
      },
      {
        "token": {
          "symbol": "USDT"
        },
        "date": 1627171200,
        "dailyVolumeUSD": "39587668.52446631914316320699531005",
        "dailyTxns": "9805",
        "priceUSD": "0.9991880355182255422978573346579863"
      },
      {
        "token": {
          "symbol": "USDT"
        },
        "date": 1627084800,
        "dailyVolumeUSD": "46737596.24238343735720689394949784",
        "dailyTxns": "10747",
        "priceUSD": "0.9999054865321679889927792673032004"
      },
      {
        "token": {
          "symbol": "USDT"
        },
        "date": 1626998400,
        "dailyVolumeUSD": "30683984.10100456321109397124848926",
        "dailyTxns": "8776",
        "priceUSD": "1.00154819752035451390710785604211"
      },
      {
        "token": {
          "symbol": "USDT"
        },
        "date": 1626912000,
        "dailyVolumeUSD": "35269644.23049099126821000655949914",
        "dailyTxns": "7659",
        "priceUSD": "1.000088522943802391099108657887538"
      },
      {
        "token": {
          "symbol": "USDT"
        },
        "date": 1626825600,
        "dailyVolumeUSD": "40348707.6253057665845621708741468",
        "dailyTxns": "9330",
        "priceUSD": "1.000010696622112236522052332292019"
      },
      {
        "token": {
          "symbol": "USDT"
        },
        "date": 1626739200,
        "dailyVolumeUSD": "40885047.84457269662011943390013092",
        "dailyTxns": "9027",
        "priceUSD": "1.001417271544284242073975147245226"
      },
      {
        "token": {
          "symbol": "USDT"
        },
        "date": 1626652800,
        "dailyVolumeUSD": "27366268.99874612804997383327732967",
        "dailyTxns": "9708",
        "priceUSD": "0.999926217716039395138556457168209"
      },
      {
        "token": {
          "symbol": "USDT"
        },
        "date": 1626566400,
        "dailyVolumeUSD": "27402363.06099803564103066451695229",
        "dailyTxns": "8683",
        "priceUSD": "1.000146604323633842375080407659407"
      },
      {
        "token": {
          "symbol": "USDT"
        },
        "date": 1626480000,
        "dailyVolumeUSD": "32181464.78311035415379902438757039",
        "dailyTxns": "9428",
        "priceUSD": "0.9999928735615529262243574756623169"
      },
      {
        "token": {
          "symbol": "USDT"
        },
        "date": 1626393600,
        "dailyVolumeUSD": "38948177.29066415476582469897561964",
        "dailyTxns": "11885",
        "priceUSD": "0.9999435543175536136840464703041674"
      },
      {
        "token": {
          "symbol": "USDT"
        },
        "date": 1626307200,
        "dailyVolumeUSD": "56793689.92165223897523954790027901",
        "dailyTxns": "12659",
        "priceUSD": "0.999802820849881859186772851544239"
      },
      {
        "token": {
          "symbol": "USDT"
        },
        "date": 1626220800,
        "dailyVolumeUSD": "42850904.71772560256100013985543118",
        "dailyTxns": "9420",
        "priceUSD": "0.9998331734665942331871824947931318"
      },
      {
        "token": {
          "symbol": "USDT"
        },
        "date": 1626134400,
        "dailyVolumeUSD": "37427766.76117888443017320420242712",
        "dailyTxns": "8101",
        "priceUSD": "1.00050473122892062772050985785591"
      },
      {
        "token": {
          "symbol": "USDT"
        },
        "date": 1626048000,
        "dailyVolumeUSD": "36313249.37358670800690195062879175",
        "dailyTxns": "8677",
        "priceUSD": "0.9994899634960476111710353166927944"
      },
      {
        "token": {
          "symbol": "USDT"
        },
        "date": 1625961600,
        "dailyVolumeUSD": "25192545.56576958530828185476776643",
        "dailyTxns": "8948",
        "priceUSD": "1.000269633002105277672941036609168"
      },
      {
        "token": {
          "symbol": "USDT"
        },
        "date": 1625875200,
        "dailyVolumeUSD": "41758259.91289708712090462360368471",
        "dailyTxns": "9766",
        "priceUSD": "0.9999350891723120680034570182426395"
      },
      {
        "token": {
          "symbol": "USDT"
        },
        "date": 1625788800,
        "dailyVolumeUSD": "52844507.11539945605282528502544406",
        "dailyTxns": "13394",
        "priceUSD": "0.9998606383484087783113808933256493"
      },
      {
        "token": {
          "symbol": "USDT"
        },
        "date": 1625702400,
        "dailyVolumeUSD": "57125727.97235140204443428090361022",
        "dailyTxns": "11017",
        "priceUSD": "0.9995401236140793285034928618969221"
      },
      {
        "token": {
          "symbol": "USDT"
        },
        "date": 1625616000,
        "dailyVolumeUSD": "59688892.66358803368240367547870527",
        "dailyTxns": "9939",
        "priceUSD": "0.999025217893303361777473227282533"
      },
      {
        "token": {
          "symbol": "USDT"
        },
        "date": 1625529600,
        "dailyVolumeUSD": "61330172.2342578901371046878157976",
        "dailyTxns": "9694",
        "priceUSD": "0.9990250241011422453409985160010139"
      },
      {
        "token": {
          "symbol": "USDT"
        },
        "date": 1625443200,
        "dailyVolumeUSD": "55790349.7452445758618356014814356",
        "dailyTxns": "12403",
        "priceUSD": "0.9995560371931112119527781267202071"
      },
      {
        "token": {
          "symbol": "USDT"
        },
        "date": 1625356800,
        "dailyVolumeUSD": "53130580.52449761268359913051927908",
        "dailyTxns": "13200",
        "priceUSD": "1.000153171375392589909605986876921"
      },
      {
        "token": {
          "symbol": "USDT"
        },
        "date": 1625270400,
        "dailyVolumeUSD": "74703203.06236957820994090849253956",
        "dailyTxns": "16094",
        "priceUSD": "0.9999044949555105648883053729854315"
      },
      {
        "token": {
          "symbol": "USDT"
        },
        "date": 1625184000,
        "dailyVolumeUSD": "67836201.86120910397017434464402554",
        "dailyTxns": "13562",
        "priceUSD": "0.9998316645938432406487522661640884"
      },
      {
        "token": {
          "symbol": "USDT"
        },
        "date": 1625097600,
        "dailyVolumeUSD": "73883495.75225699076274299964750411",
        "dailyTxns": "13395",
        "priceUSD": "1.000077241336911875743295259070238"
      },
      {
        "token": {
          "symbol": "USDT"
        },
        "date": 1625011200,
        "dailyVolumeUSD": "77796530.99345853681166898608598122",
        "dailyTxns": "12304",
        "priceUSD": "0.9998014359707255075467882956279595"
      },
      {
        "token": {
          "symbol": "USDT"
        },
        "date": 1624924800,
        "dailyVolumeUSD": "72068032.16306022174468238050818922",
        "dailyTxns": "12150",
        "priceUSD": "1.001197159631814652921422791705702"
      },
      {
        "token": {
          "symbol": "USDT"
        },
        "date": 1624838400,
        "dailyVolumeUSD": "74860983.1879295974633294323120429",
        "dailyTxns": "12204",
        "priceUSD": "1.000769050328002515708725116483471"
      },
      {
        "token": {
          "symbol": "USDT"
        },
        "date": 1624752000,
        "dailyVolumeUSD": "76424796.44777368668689263836360767",
        "dailyTxns": "12419",
        "priceUSD": "0.9997316425910500346922991894108536"
      },
      {
        "token": {
          "symbol": "USDT"
        },
        "date": 1624665600,
        "dailyVolumeUSD": "79995652.10953767676023507248412862",
        "dailyTxns": "13210",
        "priceUSD": "0.9995090491680938734991867695911779"
      },
      {
        "token": {
          "symbol": "USDT"
        },
        "date": 1624579200,
        "dailyVolumeUSD": "99125408.00077182204588780434234507",
        "dailyTxns": "15348",
        "priceUSD": "0.9998366735486272312595516296968102"
      },
      {
        "token": {
          "symbol": "USDT"
        },
        "date": 1624492800,
        "dailyVolumeUSD": "82298355.3545321118092050222511748",
        "dailyTxns": "15245",
        "priceUSD": "0.9997598511217172556816119823822043"
      },
      {
        "token": {
          "symbol": "USDT"
        },
        "date": 1624406400,
        "dailyVolumeUSD": "80820243.54324188671299108316213695",
        "dailyTxns": "14310",
        "priceUSD": "0.9996566212654875369389220888857242"
      },
      {
        "token": {
          "symbol": "USDT"
        },
        "date": 1624320000,
        "dailyVolumeUSD": "153471418.3106005264419016140193879",
        "dailyTxns": "17160",
        "priceUSD": "0.9995622563164173598717512718446653"
      },
      {
        "token": {
          "symbol": "USDT"
        },
        "date": 1624233600,
        "dailyVolumeUSD": "185272541.5992712910229384644695963",
        "dailyTxns": "21183",
        "priceUSD": "0.9989843239234747982572592038803559"
      },
      {
        "token": {
          "symbol": "USDT"
        },
        "date": 1624147200,
        "dailyVolumeUSD": "73416132.60087162631762138089526953",
        "dailyTxns": "14760",
        "priceUSD": "1.000064365945179613953793526545031"
      },
      {
        "token": {
          "symbol": "USDT"
        },
        "date": 1624060800,
        "dailyVolumeUSD": "74197216.66219990716694803684723928",
        "dailyTxns": "15846",
        "priceUSD": "1.000483382419048025720565759329843"
      },
      {
        "token": {
          "symbol": "USDT"
        },
        "date": 1623974400,
        "dailyVolumeUSD": "134077502.3585676758161545690739598",
        "dailyTxns": "19629",
        "priceUSD": "1.001882351655182082379030475000539"
      },
      {
        "token": {
          "symbol": "USDT"
        },
        "date": 1623888000,
        "dailyVolumeUSD": "216545749.1034449262461945357937505",
        "dailyTxns": "27059",
        "priceUSD": "0.9991196584145531802771345363211143"
      },
      {
        "token": {
          "symbol": "USDT"
        },
        "date": 1623801600,
        "dailyVolumeUSD": "89362650.51546162033517378778206682",
        "dailyTxns": "14542",
        "priceUSD": "1.000198811494727566629667811873048"
      },
      {
        "token": {
          "symbol": "USDT"
        },
        "date": 1623715200,
        "dailyVolumeUSD": "47424552.24652547547380510189913897",
        "dailyTxns": "11485",
        "priceUSD": "0.9995582119627241252874747669686422"
      },
      {
        "token": {
          "symbol": "USDT"
        },
        "date": 1623628800,
        "dailyVolumeUSD": "45704396.91541579030677241134561061",
        "dailyTxns": "11997",
        "priceUSD": "0.999351301755982870089154480140513"
      },
      {
        "token": {
          "symbol": "USDT"
        },
        "date": 1623542400,
        "dailyVolumeUSD": "45514366.89509947841046156717856572",
        "dailyTxns": "11124",
        "priceUSD": "1.000034917631577676982323624981054"
      },
      {
        "token": {
          "symbol": "USDT"
        },
        "date": 1623456000,
        "dailyVolumeUSD": "61462789.65011467825933965208130611",
        "dailyTxns": "12113",
        "priceUSD": "0.9999327857860289113593811723320153"
      },
      {
        "token": {
          "symbol": "USDT"
        },
        "date": 1623369600,
        "dailyVolumeUSD": "63601337.18553302504852011480750578",
        "dailyTxns": "13052",
        "priceUSD": "0.9987299100681003926162974958773797"
      },
      {
        "token": {
          "symbol": "USDT"
        },
        "date": 1623283200,
        "dailyVolumeUSD": "69783323.40267805895189813328767229",
        "dailyTxns": "13442",
        "priceUSD": "1.000403057750345970069818989070166"
      },
      {
        "token": {
          "symbol": "USDT"
        },
        "date": 1623196800,
        "dailyVolumeUSD": "68887097.2788967909444416966850948",
        "dailyTxns": "12876",
        "priceUSD": "1.000138604354324264192046402881577"
      },
      {
        "token": {
          "symbol": "USDT"
        },
        "date": 1623110400,
        "dailyVolumeUSD": "104257542.8225604904476800245923715",
        "dailyTxns": "16439",
        "priceUSD": "1.000613056659096430764072880360498"
      },
      {
        "token": {
          "symbol": "USDT"
        },
        "date": 1623024000,
        "dailyVolumeUSD": "76923373.54697932917412812745936787",
        "dailyTxns": "14562",
        "priceUSD": "1.000529869090408887029526741030736"
      },
      {
        "token": {
          "symbol": "USDT"
        },
        "date": 1622937600,
        "dailyVolumeUSD": "37454359.7114907478314389455037687",
        "dailyTxns": "10689",
        "priceUSD": "1.000305538226719135197687050938955"
      },
      {
        "token": {
          "symbol": "USDT"
        },
        "date": 1622851200,
        "dailyVolumeUSD": "63407614.43351268161763465282697068",
        "dailyTxns": "12395",
        "priceUSD": "0.9991942947526000671078326240623515"
      },
      {
        "token": {
          "symbol": "USDT"
        },
        "date": 1622764800,
        "dailyVolumeUSD": "85574446.19767493418525125004376597",
        "dailyTxns": "13193",
        "priceUSD": "0.9993117216212552765870420655147126"
      },
      {
        "token": {
          "symbol": "USDT"
        },
        "date": 1622678400,
        "dailyVolumeUSD": "72856042.94020000131541579448822347",
        "dailyTxns": "13540",
        "priceUSD": "0.999950123515149708631721112692222"
      },
      {
        "token": {
          "symbol": "USDT"
        },
        "date": 1622592000,
        "dailyVolumeUSD": "63236798.92926281285266976405953926",
        "dailyTxns": "12544",
        "priceUSD": "0.9988985945803127376944196397782893"
      },
      {
        "token": {
          "symbol": "USDT"
        },
        "date": 1622505600,
        "dailyVolumeUSD": "76655028.02002031868426459135405448",
        "dailyTxns": "12519",
        "priceUSD": "1.001277717165246561809358298107466"
      },
      {
        "token": {
          "symbol": "USDT"
        },
        "date": 1622419200,
        "dailyVolumeUSD": "86501139.66156657115952336674602243",
        "dailyTxns": "13616",
        "priceUSD": "0.9999010102384306201523708397857324"
      },
      {
        "token": {
          "symbol": "USDT"
        },
        "date": 1622332800,
        "dailyVolumeUSD": "89667800.6728030876847701068106878",
        "dailyTxns": "13248",
        "priceUSD": "1.000575502337477039187142813001782"
      },
      {
        "token": {
          "symbol": "USDT"
        },
        "date": 1622246400,
        "dailyVolumeUSD": "115310308.563154050956933491063979",
        "dailyTxns": "14586",
        "priceUSD": "1.000284667181695510463436782307302"
      },
      {
        "token": {
          "symbol": "USDT"
        },
        "date": 1622160000,
        "dailyVolumeUSD": "137899755.2110684431856540414817353",
        "dailyTxns": "15000",
        "priceUSD": "1.000266490354610668537509132611089"
      },
      {
        "token": {
          "symbol": "USDT"
        },
        "date": 1622073600,
        "dailyVolumeUSD": "136097882.7118510338334226723560268",
        "dailyTxns": "13406",
        "priceUSD": "1.000164489011571204755576507815749"
      },
      {
        "token": {
          "symbol": "USDT"
        },
        "date": 1621987200,
        "dailyVolumeUSD": "336290176.3064626180162523448485721",
        "dailyTxns": "15148",
        "priceUSD": "1.000465180653830496064821926227402"
      },
      {
        "token": {
          "symbol": "USDT"
        },
        "date": 1621900800,
        "dailyVolumeUSD": "161433888.0977914353302574814078864",
        "dailyTxns": "16114",
        "priceUSD": "0.9999858909051568268421083691176377"
      }
    ]
  }
}